chime_logger/__init__.py
chime_logger/config.py
chime_logger/const.py
chime_logger/context.py
chime_logger/emitters.py
chime_logger/filters.py
chime_logger/handlers.py
chime_logger-0.4.0.dist-info/METADATA
chime_logger-0.4.0.dist-info/WHEEL
chime_logger-0.4.0.dist-info/licenses/LICENSE
chime_logger-0.4.0.dist-info/RECORD
