Metadata-Version: 2.4
Name: chime_logger
Version: 0.4.0
Summary: A python logger for CHIME/FRB with Loki support.
License: MIT
License-File: LICENSE
Author: Tarik Zegmott
Author-email: tarik.zegmott@mcgill.ca
Requires-Python: >=3.6,<4.0
Classifier: License :: OSI Approved :: MIT License
Classifier: Programming Language :: Python :: 3
Classifier: Programming Language :: Python :: 3.6
Classifier: Programming Language :: Python :: 3.7
Classifier: Programming Language :: Python :: 3.8
Classifier: Programming Language :: Python :: 3.9
Classifier: Programming Language :: Python :: 3.10
Classifier: Programming Language :: Python :: 3.11
Classifier: Programming Language :: Python :: 3.12
Classifier: Programming Language :: Python :: 3.13
Classifier: Programming Language :: Python :: 3.14
Requires-Dist: pydantic (>=1.7)
Requires-Dist: requests (>=2.27.1)
Requires-Dist: rfc3339 (>=6.1)
Requires-Dist: urllib3 (>=1.26.14,<2.0)
